{
  "name": "maisonnette:catacombs/hall_pool",
  "fallback": "minecraft:empty",
  "elements": [
    {
      "weight": 2,
      "element": {
        "element_type": "minecraft:single_pool_element",
        "projection": "rigid",
        "location": "maisonnette:catacombs/hallway/four_way_hall",
        "processors": "minecraft:empty"
      }
    },
    {
      "weight": 3,
      "element": {
        "element_type": "minecraft:single_pool_element",
        "projection": "rigid",
        "location": "maisonnette:catacombs/hallway/corner_hall",
        "processors": "minecraft:empty"
      }
    },
    {
      "weight": 2,
      "element": {
        "element_type": "minecraft:single_pool_element",
        "projection": "rigid",
        "location": "maisonnette:catacombs/hallway/catacombs_staircases",
        "processors": "minecraft:empty"
      }
    },
    {
      "weight": 4,
      "element": {
        "element_type": "minecraft:single_pool_element",
        "projection": "rigid",
        "location": "maisonnette:catacombs/hallway/hall_short",
        "processors": "minecraft:empty"
      }
    },
    {
      "weight": 5,
      "element": {
        "element_type": "minecraft:single_pool_element",
        "projection": "rigid",
        "location": "maisonnette:catacombs/hallway/catacombs_long_hall",
        "processors": "minecraft:empty"
      }
    }
  ]
}